messageboard.py
messageboard-0.1.0a0.dist-info/licenses/LICENSE
messageboard-0.1.0a0.dist-info/METADATA
messageboard-0.1.0a0.dist-info/WHEEL
messageboard-0.1.0a0.dist-info/top_level.txt
messageboard-0.1.0a0.dist-info/RECORD
