Metadata-Version: 2.4
Name: messageboard
Version: 0.1.0a0
Summary: A synchronization primitive containing a value, allowing threads to concurrently set the value and peek the most recently set value.
Author-email: Jifeng Wu <jifengwu2k@gmail.com>
License-Expression: MIT
Project-URL: Homepage, https://github.com/jifengwu2k/messageboard
Project-URL: Bug Tracker, https://github.com/jifengwu2k/messageboard/issues
Classifier: Programming Language :: Python :: 2
Classifier: Programming Language :: Python :: 3
Classifier: Operating System :: OS Independent
Requires-Python: >=2
License-File: LICENSE
Dynamic: license-file
